corbel/__init__.py
corbel/_objects/__init__.py
corbel/_objects/_property.py
corbel/_utils/__init__.py
corbel/_utils/_asdict.py
corbel/_utils/_capture_member.py
corbel/_utils/_capture_obj.py
corbel/_utils/_corbel_metadata.py
corbel/_utils/_default_value.py
corbel/_utils/_deserialize_dataclass.py
corbel/_utils/_deserialize_field.py
corbel/_utils/_deserialize_obj.py
corbel/_utils/_deserialize_value.py
corbel/_utils/_field.py
corbel/_utils/_field.pyi
corbel/_utils/_fields.py
corbel/_utils/_from_dict.py
corbel/_utils/_from_json.py
corbel/_utils/_include_member.py
corbel/_utils/_is_required.py
corbel/_utils/_resolve_field_key.py
corbel/_utils/_serialize_obj.py
corbel/_utils/_to_dict.py
corbel/_utils/_to_json.py
corbel/decorators/__init__.py
corbel/decorators/_dataclass.py
corbel/decorators/_dataclass.pyi.py
corbel/decorators/_property.py
corbel/enums/__init__.py
corbel/enums/_include.py
corbel/errors/__init__.py
corbel/errors/_corbel.py
corbel/errors/_deserialize.py
corbel/errors/_inclusion.py
corbel/errors/_validation.py
corbel/mixins/__init__.py
corbel/mixins/_base.py
corbel/mixins/_comparable.py
corbel/mixins/_corbel.py
corbel/mixins/_hashable.py
corbel/mixins/_hooks.py
corbel/mixins/_members.py
corbel/mixins/_meta.py
corbel/mixins/_serializable.py
corbel/mixins/_updatable.py
corbel/mixins/_validated.py
corbel/protocols/__init__.py
corbel/protocols/_dataclass.py
corbel/protocols/_deserializer.py
corbel/protocols/_hooks.py
corbel/protocols/_member.py
corbel/protocols/_serializer.py
corbel/protocols/_validator.py
corbel/types.py
corbel-0.1.3.dist-info/LICENSE
corbel-0.1.3.dist-info/METADATA
corbel-0.1.3.dist-info/WHEEL
corbel-0.1.3.dist-info/RECORD
