Metadata-Version: 2.1
Name: corbel
Version: 0.1.3
Summary: Lightweight Python library extending dataclasses with serialization, deserialization, validation, and mixins for comparison, hashing, and immutable updates.
Home-page: https://github.com/bnlucas/corbel
License: MIT
Keywords: dataclass,serialization,deserialization,validation,mixin,python
Author: Nathan Lucas
Author-email: nlucas@bnlucas.com
Requires-Python: >=3.10,<4.0
Classifier: Development Status :: 4 - Beta
Classifier: License :: OSI Approved :: MIT License
Classifier: Operating System :: OS Independent
Classifier: Programming Language :: Python :: 3
Classifier: Programming Language :: Python :: 3.10
Classifier: Programming Language :: Python :: 3.11
Classifier: Programming Language :: Python :: 3.12
Classifier: Typing :: Typed
Project-URL: Repository, https://github.com/bnlucas/corbel
